<annotation>
	<folder>train</folder>
	<filename>1.png</filename>
	<path>/home/miguel-bge/Desktop/object_detection_BGE/data/images/train/1.png</path>
	<source>
		<database>Unknown</database>
	</source>
	<size>
		<width>960</width>
		<height>540</height>
		<depth>3</depth>
	</size>
	<segmented>0</segmented>
	<object>
		<name>asarp_marker</name>
		<pose>Unspecified</pose>
		<truncated>0</truncated>
		<difficult>0</difficult>
		<bndbox>
			<xmin>634</xmin>
			<ymin>223</ymin>
			<xmax>660</xmax>
			<ymax>249</ymax>
		</bndbox>
	</object>
	<object>
		<name>asarp_marker</name>
		<pose>Unspecified</pose>
		<truncated>0</truncated>
		<difficult>0</difficult>
		<bndbox>
			<xmin>656</xmin>
			<ymin>268</ymin>
			<xmax>682</xmax>
			<ymax>293</ymax>
		</bndbox>
	</object>
	<object>
		<name>asarp_marker</name>
		<pose>Unspecified</pose>
		<truncated>0</truncated>
		<difficult>0</difficult>
		<bndbox>
			<xmin>656</xmin>
			<ymin>314</ymin>
			<xmax>689</xmax>
			<ymax>337</ymax>
		</bndbox>
	</object>
	<object>
		<name>asarp_marker</name>
		<pose>Unspecified</pose>
		<truncated>0</truncated>
		<difficult>0</difficult>
		<bndbox>
			<xmin>518</xmin>
			<ymin>224</ymin>
			<xmax>545</xmax>
			<ymax>257</ymax>
		</bndbox>
	</object>
	<object>
		<name>asarp_marker</name>
		<pose>Unspecified</pose>
		<truncated>0</truncated>
		<difficult>0</difficult>
		<bndbox>
			<xmin>560</xmin>
			<ymin>215</ymin>
			<xmax>586</xmax>
			<ymax>242</ymax>
		</bndbox>
	</object>
	<object>
		<name>asarp_marker</name>
		<pose>Unspecified</pose>
		<truncated>0</truncated>
		<difficult>0</difficult>
		<bndbox>
			<xmin>504</xmin>
			<ymin>265</ymin>
			<xmax>533</xmax>
			<ymax>296</ymax>
		</bndbox>
	</object>
	<object>
		<name>asarp_marker</name>
		<pose>Unspecified</pose>
		<truncated>0</truncated>
		<difficult>0</difficult>
		<bndbox>
			<xmin>500</xmin>
			<ymin>311</ymin>
			<xmax>523</xmax>
			<ymax>334</ymax>
		</bndbox>
	</object>
	<object>
		<name>asarp_marker</name>
		<pose>Unspecified</pose>
		<truncated>0</truncated>
		<difficult>0</difficult>
		<bndbox>
			<xmin>508</xmin>
			<ymin>345</ymin>
			<xmax>523</xmax>
			<ymax>365</ymax>
		</bndbox>
	</object>
	<object>
		<name>asarp_marker</name>
		<pose>Unspecified</pose>
		<truncated>0</truncated>
		<difficult>0</difficult>
		<bndbox>
			<xmin>519</xmin>
			<ymin>380</ymin>
			<xmax>540</xmax>
			<ymax>395</ymax>
		</bndbox>
	</object>
	<object>
		<name>asarp_marker</name>
		<pose>Unspecified</pose>
		<truncated>0</truncated>
		<difficult>0</difficult>
		<bndbox>
			<xmin>571</xmin>
			<ymin>365</ymin>
			<xmax>595</xmax>
			<ymax>389</ymax>
		</bndbox>
	</object>
	<object>
		<name>asarp_marker</name>
		<pose>Unspecified</pose>
		<truncated>0</truncated>
		<difficult>0</difficult>
		<bndbox>
			<xmin>656</xmin>
			<ymin>354</ymin>
			<xmax>678</xmax>
			<ymax>378</ymax>
		</bndbox>
	</object>
</annotation>
